CHANGES.txt
MANIFEST.in
setup.py
fassembler_projects/__init__.py
fassembler_projects/frontend.py
fassembler_projects/zine.py
fassembler_projects/templates/frontend/paste.ini_tmpl
fassembler_projects/templates/zine/paste.ini_tmpl
opencore_fassembler_projects.egg-info/PKG-INFO
opencore_fassembler_projects.egg-info/SOURCES.txt
opencore_fassembler_projects.egg-info/dependency_links.txt
opencore_fassembler_projects.egg-info/entry_points.txt
opencore_fassembler_projects.egg-info/not-zip-safe
opencore_fassembler_projects.egg-info/requires.txt
opencore_fassembler_projects.egg-info/top_level.txt