Metadata-Version: 1.0
Name: opencore-fassembler-projects
Version: 0.5
Summary: Assorted fassembler projects for creating repeatable OpenCore builds
Home-page: http://coactivate.org/projects/opencore
Author: Ethan Jucovy
Author-email: opencore-dev@lists.coactivate.org
License: GPL
Platform: UNKNOWN
